fasthelloworld/__init__.py
fasthelloworld/main.py
fasthelloworld-0.1.0.dist-info/METADATA
fasthelloworld-0.1.0.dist-info/WHEEL
fasthelloworld-0.1.0.dist-info/RECORD
